MANIFEST.in
README.txt
VERSION
setup.py
etsmtl/__init__.py
etsmtl/version.py
etsmtl.egg-info/PKG-INFO
etsmtl.egg-info/SOURCES.txt
etsmtl.egg-info/dependency_links.txt
etsmtl.egg-info/requires.txt
etsmtl.egg-info/top_level.txt
etsmtl/data/ca-certificates.crt