Metadata-Version: 1.0
Name: etsmtl
Version: 0.1.1
Summary: ETSMTL python bindings
Home-page: UNKNOWN
Author: UNKNOWN
Author-email: UNKNOWN
License: UNKNOWN
Platform: UNKNOWN
